[
    {
        "nombre": "Leonardo",
        "carne": "Carne",
        "papas": "Cheddar",
        "bebida": "Agua"
    },
    {
        "nombre": "Marcos",
        "carne": "Carne",
        "papas": "Cheddar",
        "bebida": "Agua"
    },
    {
        "nombre": "Laura",
        "carne": "Carne",
        "papas": "Cheddar",
        "bebida": "Agua"
    },
    {
        "nombre": "Ramiro",
        "carne": "Carne",
        "papas": "Cheddar",
        "bebida": "Agua"
    }
]